actions/__init__.py
actions/diff/__init__.py
actions/diff/action.py
actions/dummy/__init__.py
actions/dummy/action.py
actions/ratio/__init__.py
actions/ratio/action.py
comparators/__init__.py
comparators/gt_number/__init__.py
comparators/gt_number/comparator.py
comparators/gt_zero/__init__.py
comparators/gt_zero/comparator.py
comparators/gte_zero/__init__.py
comparators/gte_zero/comparator.py
comparators/is_true/__init__.py
comparators/is_true/comparator.py
comparators/not_zero/__init__.py
comparators/not_zero/comparator.py
dqchecker-0.0.1.dist-info/METADATA
dqchecker-0.0.1.dist-info/WHEEL
dqchecker-0.0.1.dist-info/top_level.txt
dqchecker-0.0.1.dist-info/RECORD
